MANIFEST.in
README.md
requirements.txt
setup.py
byteblower/__init__.py
byteblower/byteblowerll/__init__.py
byteblower/byteblowerll/_byteblower.pyd
byteblower/byteblowerll/byteblower.py
pybyteblower.egg-info/PKG-INFO
pybyteblower.egg-info/SOURCES.txt
pybyteblower.egg-info/dependency_links.txt
pybyteblower.egg-info/requires.txt
pybyteblower.egg-info/top_level.txt