Metadata-Version: 1.1
Name: pybyteblower
Version: 0.1
Summary: Pip installable package wrapping ByteBlower traffic generator Python API
Home-page: https://github.com/shmir/PyByteBlower/
Author: Yoram Shamir
Author-email: yoram@ignissoft.com
License: Apache Software License
Keywords: byteblower l2l3 test tool automation
Platform: nt
Classifier: Programming Language :: Python
Classifier: Development Status :: 4 - Beta
Classifier: Natural Language :: English
Classifier: Intended Audience :: Developers
Classifier: License :: OSI Approved :: Apache Software License
Classifier: Operating System :: OS Independent
Classifier: Programming Language :: Python :: 2.7
Classifier: Topic :: Software Development :: Testing :: Traffic Generation
